us_sign_language/__init__.py
us_sign_language/main.py
us_sign_language-0.1.dist-info/METADATA
us_sign_language-0.1.dist-info/WHEEL
us_sign_language-0.1.dist-info/top_level.txt
us_sign_language-0.1.dist-info/RECORD
