Metadata-Version: 2.1
Name: us_sign_language
Version: 0.1
Requires-Dist: tensorflow <=2.8.0
Requires-Dist: mediapipe <=0.8.11
Requires-Dist: numpy >=1.19.3
Requires-Dist: opencv-python >=4.9.0.80
Requires-Dist: asyncio >=3.4.3
